src/demux_1x8.v
`default_nettype none

module demux_1x8 (
    input  wire       i,
    input  wire [2:0] s,
    output wire [7:0] o
);
    // Preserve the lab ordering: 000->o[7], ..., 111->o[0].
    assign o = i ? (8'b10000000 >> s) : 8'b00000000;
endmodule

`default_nettype wire

sim/tb_demux_1x8.sv
`timescale 1ns/1ps
`default_nettype none

module tb_demux_1x8;
    logic       i;
    logic [2:0] s;
    wire  [7:0] o;

    integer n;
    integer checked;
    logic [7:0] expected;

    demux_1x8 dut (.i(i), .s(s), .o(o));

    initial begin
        $dumpfile("wave.vcd");
        $dumpvars(0, tb_demux_1x8);
        i = 1'b0;
        s = 3'b000;
        checked = 0;

        for (n = 0; n < 16; n = n + 1) begin
            {i, s} = n[3:0];
            expected = (n >= 8) ? (8'b10000000 >> (n % 8)) : 8'b00000000;
            #10;
            if (o !== expected)
                $fatal(1,
                    "LAB1_FAIL demux_1x8 case=%0d i=%0b s=%03b expected=%08b actual=%08b",
                    n, i, s, expected, o);
            checked = checked + 1;
        end

        if (checked != 16)
            $fatal(1, "LAB1_FAIL demux_1x8 checked=%0d expected_cases=16", checked);
        $display("LAB1_PASS demux_1x8 cases=%0d", checked);
        $finish;
    end

    initial begin
        #300;
        $fatal(1, "LAB1_FAIL demux_1x8 watchdog timeout");
    end
endmodule

`default_nettype wire

evidence/demux_1x8/demux_1x8_recovery_wave.vcd
$date
   Sat Sep 12 02:08:19 2026
$end

$version
  2026.1
  $dumpfile ("wave.vcd") 
$end

$timescale
  1ps
$end

$scope module tb_demux_1x8 $end
$var reg 1 ! i $end
$var reg 3 " s [2:0] $end
$var wire 8 # o [7:0] $end
$var integer 32 $ n [31:0] $end
$var integer 32 % checked [31:0] $end
$var reg 8 & expected [7:0] $end
$scope module dut $end
$var wire 1 ' i $end
$var wire 3 ( s [2:0] $end
$var wire 8 # o [7:0] $end
$upscope $end
$upscope $end
$enddefinitions $end

#0
$dumpvars
0!
b0 "
b0 #
b0 $
b0 %
b0 &
0'
b0 (
$end

#10000
b1 "
b1 $
b1 %
b1 (

#20000
b10 "
b10 $
b10 %
b10 (

#30000
b11 "
b11 $
b11 %
b11 (

#40000
b100 "
b100 $
b100 %
b100 (

#50000
b101 "
b101 $
b101 %
b101 (

#60000
b110 "
b110 $
b110 %
b110 (

#70000
b111 "
b111 $
b111 %
b111 (

#80000
1!
b0 "
b10000000 #
b1000 $
b1000 %
b10000000 &
1'
b0 (

#90000
b1 "
b1000000 #
b1001 $
b1001 %
b1000000 &
b1 (

#100000
b10 "
b100000 #
b1010 $
b1010 %
b100000 &
b10 (

#110000
b11 "
b10000 #
b1011 $
b1011 %
b10000 &
b11 (

#120000
b100 "
b1000 #
b1100 $
b1100 %
b1000 &
b100 (

#130000
b101 "
b100 #
b1101 $
b1101 %
b100 &
b101 (

#140000
b110 "
b10 #
b1110 $
b1110 %
b10 &
b110 (

#150000
b111 "
b1 #
b1111 $
b1111 %
b1 &
b111 (

#160000
b10000 $
b10000 %
